jhdfs4py/__init__.py
jhdfs4py/hdfsfs.py
jhdfs4py/hdfsio.py
jhdfs4py/py.typed
jhdfs4py-1.4.1.dist-info/LICENSE
jhdfs4py-1.4.1.dist-info/METADATA
jhdfs4py-1.4.1.dist-info/WHEEL
jhdfs4py-1.4.1.dist-info/top_level.txt
jhdfs4py-1.4.1.dist-info/RECORD
