Metadata-Version: 2.1
Name: jhdfs4py
Version: 1.4.1
Summary: Convenient HDFS access using the Java HDFS client
Home-page: https://gitlab.com/stiftung-zentrale-stelle-verpackungsregister/jhdfs4py
Author-email: opensource@verpackungsregister.org
License: UNKNOWN
Platform: UNKNOWN
Classifier: Programming Language :: Python :: 3
Classifier: License :: OSI Approved :: Apache Software License
Classifier: Operating System :: OS Independent
Requires-Python: >=3.6
License-File: LICENSE
Requires-Dist: pyspark (<3.3,>=2.4)
Requires-Dist: dataclasses (>=0.7) ; python_version < "3.7"
